<idea-plugin url="https://www.github.com/ShiromMakkad/base16-jetbrains-ide">
<id>com.base16.atelier-savanna</id>
<name>Base16 Atelier Savanna</name>
<version>1.0.0</version>
<vendor>Bram de Haan (http://atelierbramdehaan.nl), Shirom Makkad, and the Base16 project</vendor>

<description><![CDATA[
  <p>Base 16 Atelier Savanna for Jetbrains IDE</p>
  <br>
  <p>---------------</p>
  <br>
  <p>Colors by Bram de Haan (http://atelierbramdehaan.nl). Theme made using base16(https://github.com/chriskempson/base16). Theme generated by Shirom Makkad (https://github.com/ShiromMakkad/base16-jetbrains-ide)</p>
    ]]>
</description>

<change-notes><![CDATA[
  <p>Version 1.0.0</p>
    ]]>
</change-notes>
<idea-version since-build="191.0"/>

<depends>com.intellij.modules.platform</depends>

  <extensions defaultExtensionNs="com.intellij">
    <themeProvider id="base16-atelier-savanna" path="/base16-atelier-savanna.theme.json"/>
  </extensions>
</idea-plugin>
